.coveragerc
.gitignore
.pre-commit-config.yaml
.travis.yml
AUTHORS.rst
CHANGELOG.rst
LICENSE.txt
Makefile
README.rst
__init__.py
pyproject.toml
requirements-dev.txt
requirements.txt
setup.cfg
setup.py
tox.ini
docs/Makefile
docs/Publishing.rst
docs/authors.rst
docs/changelog.rst
docs/conf.py
docs/index.rst
docs/license.rst
docs/wordpress.rst
docs/_static/.gitignore
src/metapack_wp/__init__.py
src/metapack_wp/aws.py
src/metapack_wp/ckan.py
src/metapack_wp/dw.py
src/metapack_wp/wp.py
src/metapack_wp.egg-info/PKG-INFO
src/metapack_wp.egg-info/SOURCES.txt
src/metapack_wp.egg-info/dependency_links.txt
src/metapack_wp.egg-info/entry_points.txt
src/metapack_wp.egg-info/not-zip-safe
src/metapack_wp.egg-info/requires.txt
src/metapack_wp.egg-info/top_level.txt
src/metapack_wp/old/__init__.py
src/metapack_wp/old/install.py
src/metapack_wp/old/install_file.py
src/metapack_wp/old/install_git.py
src/metapack_wp/support/__init__.py
src/metapack_wp/support/templates/__init__.py
src/metapack_wp/support/templates/wordpress.html
src/metapack_wp/support/templates/wordpress/contacts.html
src/metapack_wp/support/templates/wordpress/distributions.html
src/metapack_wp/support/templates/wordpress/documentation.html
src/metapack_wp/support/templates/wordpress/footer.html
src/metapack_wp/support/templates/wordpress/header.html
src/metapack_wp/support/templates/wordpress/images.html
src/metapack_wp/support/templates/wordpress/jsonld.html
src/metapack_wp/support/templates/wordpress/notes.html
src/metapack_wp/support/templates/wordpress/references.html
src/metapack_wp/support/templates/wordpress/resources.html
src/metapack_wp/support/templates/wordpress/schema.html
tests/conftest.py
tests/test_publish.py
tests/test_skeleton.py
tests/travis_install.sh