Metadata-Version: 2.1
Name: metapack-wp
Version: 0.0.16
Summary: Web publishing extension for the Metapack data mangement system
Home-page: https://github.com/Metatab/metatab-wp
Author: Eric Busboom
Author-email: eric@civicknowledge.com
License: mit
Platform: any
Classifier: Development Status :: 4 - Beta
Classifier: Programming Language :: Python
Provides-Extra: testing
